raster_geometry/__init__.py
raster_geometry/_version.py
raster_geometry/raster.py
raster_geometry-0.1.4.2.dist-info/AUTHORS.rst
raster_geometry-0.1.4.2.dist-info/LICENSE.rst
raster_geometry-0.1.4.2.dist-info/METADATA
raster_geometry-0.1.4.2.dist-info/WHEEL
raster_geometry-0.1.4.2.dist-info/top_level.txt
raster_geometry-0.1.4.2.dist-info/RECORD
