Metadata-Version: 2.1
Name: raster-geometry
Version: 0.1.4.2
Summary: Create/manipulate N-dimensional raster geometries.
Home-page: https://github.com/norok2/raster_geometry
Author: Riccardo Metere
Author-email: rick@metere.it
License: GPLv3+
Keywords: geometry,geometric,raster,shape,pixel,voxel,render,mask
Platform: UNKNOWN
Classifier: Development Status :: 4 - Beta
Classifier: Intended Audience :: Developers
Classifier: Intended Audience :: End Users/Desktop
Classifier: Intended Audience :: Science/Research
Classifier: Intended Audience :: Education
Classifier: Natural Language :: English
Classifier: Topic :: Software Development
Classifier: Topic :: Software Development :: Libraries
Classifier: Topic :: Utilities
Classifier: Operating System :: POSIX
Classifier: License :: OSI Approved :: GNU General Public License v3 or later (GPLv3+)
Classifier: Programming Language :: Python
Classifier: Programming Language :: Python :: 3
License-File: LICENSE.rst
License-File: AUTHORS.rst
Requires-Dist: appdirs
Requires-Dist: flyingcircus
Requires-Dist: flyingcircus-numeric
Requires-Dist: numpy
Requires-Dist: scipy
Requires-Dist: setuptools
Provides-Extra: blessed
Requires-Dist: blessed ; extra == 'blessed'
